spark_sink_connector/__init__.py
spark_sink_connector/enums.py
spark_sink_connector/schema_helper.py
spark_sink_connector/spark_sink_config.py
spark_sink_connector/spark_sink_connector.py
spark_sink_connector-0.11.3.dist-info/METADATA
spark_sink_connector-0.11.3.dist-info/WHEEL
spark_sink_connector-0.11.3.dist-info/top_level.txt
spark_sink_connector-0.11.3.dist-info/RECORD
