Metadata-Version: 2.4
Name: spark-sink-connector
Version: 0.11.3
Summary: A connector for reading data from Kafka and writing to S3 in Delta or Hudi format.
Home-page: https://gitlab.snapp.ir/navid.farhadi/spark-sink-connector
Author: Navid
Author-email: navid.farhadi@snapp.cab
Requires-Python: >=3.7
Dynamic: author
Dynamic: author-email
Dynamic: home-page
Dynamic: requires-python
Dynamic: summary
